[
  {
    "make": "Govecs",
    "model": "Elmoto Loop",
    "year": "2022",
    "type": "Allround",
    "displacement": null,
    "engine": "Electric",
    "compression": null,
    "bore_stroke": null,
    "valves_per_cylinder": null,
    "fuel_system": null,
    "fuel_control": null,
    "lubrication": null,
    "cooling": "Air",
    "gearbox": "1-speed",
    "transmission": null,
    "clutch": null,
    "frame": "Steel tube",
    "front_suspension": "Marzocchi double bridge-fork",
    "front_wheel_travel": null,
    "rear_suspension": "Twin-Shock buffers",
    "rear_wheel_travel": null,
    "front_tire": "2.35-24 ",
    "rear_tire": "2.34-24 ",
    "front_brakes": "Single disc",
    "rear_brakes": "Single disc",
    "seat_height": "830 mm (32.7 inches) If adjustable, lowest setting.",
    "ground_clearance": null,
    "wheelbase": null,
    "fuel_capacity": null,
    "starter": "Electric",
    "power": "2.7 HP (2.0  kW))",
    "torque": "54.0 Nm (5.5 kgf-m or 39.8 ft.lbs)",
    "top_speed": "45.0 km/h (28.0 mph)",
    "fuel_consumption": null,
    "emission": null,
    "total_weight": "59.0 kg (130.1 pounds)",
    "total_height": "1150 mm (45.3 inches)",
    "total_length": "1895 mm (74.6 inches)",
    "total_width": "716 mm (28.2 inches)",
    "ignition": null,
    "dry_weight": null
  },
  {
    "make": "Govecs",
    "model": "Flex",
    "year": "2021",
    "type": "Scooter",
    "displacement": null,
    "engine": "Electric",
    "compression": null,
    "bore_stroke": null,
    "valves_per_cylinder": null,
    "fuel_system": null,
    "fuel_control": null,
    "lubrication": null,
    "cooling": "Air",
    "gearbox": "1-speed",
    "transmission": "Belt   (final drive)",
    "clutch": null,
    "frame": "Steel tube",
    "front_suspension": "Hydraulic telescope",
    "front_wheel_travel": null,
    "rear_suspension": "Hydraulic dual shocks",
    "rear_wheel_travel": null,
    "front_tire": "130/60-16 ",
    "rear_tire": "130/60-16 ",
    "front_brakes": "Single disc",
    "rear_brakes": "Single disc",
    "seat_height": "780 mm (30.7 inches) If adjustable, lowest setting.",
    "ground_clearance": null,
    "wheelbase": null,
    "fuel_capacity": null,
    "starter": "Electric",
    "power": "2.7 HP (2.0  kW))",
    "torque": "54.0 Nm (5.5 kgf-m or 39.8 ft.lbs)",
    "top_speed": "45.0 km/h (28.0 mph)",
    "fuel_consumption": null,
    "emission": null,
    "total_weight": null,
    "total_height": "1300 mm (51.2 inches)",
    "total_length": "1890 mm (74.4 inches)",
    "total_width": "680 mm (26.8 inches)",
    "ignition": null,
    "dry_weight": "95.0 kg (209.4 pounds)"
  },
  {
    "make": "Govecs",
    "model": "E-Schwalbe",
    "year": "2020",
    "type": "Scooter",
    "displacement": null,
    "engine": "Electric",
    "compression": null,
    "bore_stroke": null,
    "valves_per_cylinder": null,
    "fuel_system": null,
    "fuel_control": null,
    "lubrication": null,
    "cooling": "Air",
    "gearbox": "1-speed",
    "transmission": "Belt   (final drive)",
    "clutch": null,
    "frame": "Steel tube",
    "front_suspension": "Hydraulic telescope",
    "front_wheel_travel": null,
    "rear_suspension": "Hydraulic monoshock",
    "rear_wheel_travel": null,
    "front_tire": "100/80-R16 ",
    "rear_tire": "100/80-R16 ",
    "front_brakes": "Single disc. ABS",
    "rear_brakes": "Single disc. ABS",
    "seat_height": "840 mm (33.1 inches) If adjustable, lowest setting.",
    "ground_clearance": null,
    "wheelbase": null,
    "fuel_capacity": null,
    "starter": "Electric",
    "power": "5.4 HP (3.9  kW))",
    "torque": "54.0 Nm (5.5 kgf-m or 39.8 ft.lbs)",
    "top_speed": "45.0 km/h (28.0 mph)",
    "fuel_consumption": null,
    "emission": null,
    "total_weight": "135.0 kg (297.6 pounds)",
    "total_height": "1130 mm (44.5 inches)",
    "total_length": "1960 mm (77.2 inches)",
    "total_width": "880 mm (34.6 inches)",
    "ignition": null,
    "dry_weight": null
  },
  {
    "make": "Govecs",
    "model": "Elmoto Loop",
    "year": "2020",
    "type": "Allround",
    "displacement": null,
    "engine": "Electric",
    "compression": null,
    "bore_stroke": null,
    "valves_per_cylinder": null,
    "fuel_system": null,
    "fuel_control": null,
    "lubrication": null,
    "cooling": "Air",
    "gearbox": "1-speed",
    "transmission": null,
    "clutch": null,
    "frame": "Steel tube",
    "front_suspension": "Marzocchi double bridge-fork",
    "front_wheel_travel": null,
    "rear_suspension": "Twin-Shock buffers",
    "rear_wheel_travel": null,
    "front_tire": "2.35-24 ",
    "rear_tire": "2.34-24 ",
    "front_brakes": "Single disc",
    "rear_brakes": "Single disc",
    "seat_height": "830 mm (32.7 inches) If adjustable, lowest setting.",
    "ground_clearance": null,
    "wheelbase": null,
    "fuel_capacity": null,
    "starter": "Electric",
    "power": "2.7 HP (2.0  kW))",
    "torque": "54.0 Nm (5.5 kgf-m or 39.8 ft.lbs)",
    "top_speed": "45.0 km/h (28.0 mph)",
    "fuel_consumption": null,
    "emission": null,
    "total_weight": "59.0 kg (130.1 pounds)",
    "total_height": "1150 mm (45.3 inches)",
    "total_length": "1895 mm (74.6 inches)",
    "total_width": "716 mm (28.2 inches)",
    "ignition": null,
    "dry_weight": null
  },
  {
    "make": "Govecs",
    "model": "Flex",
    "year": "2020",
    "type": "Scooter",
    "displacement": null,
    "engine": "Electric",
    "compression": null,
    "bore_stroke": null,
    "valves_per_cylinder": null,
    "fuel_system": null,
    "fuel_control": null,
    "lubrication": null,
    "cooling": "Air",
    "gearbox": "1-speed",
    "transmission": "Belt   (final drive)",
    "clutch": null,
    "frame": "Steel tube",
    "front_suspension": "Hydraulic telescope",
    "front_wheel_travel": null,
    "rear_suspension": "Hydraulic dual shocks",
    "rear_wheel_travel": null,
    "front_tire": "130/60-16 ",
    "rear_tire": "130/60-16 ",
    "front_brakes": "Single disc",
    "rear_brakes": "Single disc",
    "seat_height": "780 mm (30.7 inches) If adjustable, lowest setting.",
    "ground_clearance": null,
    "wheelbase": null,
    "fuel_capacity": null,
    "starter": "Electric",
    "power": "2.7 HP (2.0  kW))",
    "torque": "54.0 Nm (5.5 kgf-m or 39.8 ft.lbs)",
    "top_speed": "45.0 km/h (28.0 mph)",
    "fuel_consumption": null,
    "emission": null,
    "total_weight": null,
    "total_height": "1300 mm (51.2 inches)",
    "total_length": "1890 mm (74.4 inches)",
    "total_width": "680 mm (26.8 inches)",
    "ignition": null,
    "dry_weight": "95.0 kg (209.4 pounds)"
  },
  {
    "make": "Govecs",
    "model": "Pro",
    "year": "2020",
    "type": "Scooter",
    "displacement": null,
    "engine": "Electric",
    "compression": null,
    "bore_stroke": null,
    "valves_per_cylinder": null,
    "fuel_system": null,
    "fuel_control": null,
    "lubrication": null,
    "cooling": "Air",
    "gearbox": "1-speed",
    "transmission": "Belt   (final drive)",
    "clutch": null,
    "frame": "Steel tube",
    "front_suspension": "Hydraulic telescope",
    "front_wheel_travel": null,
    "rear_suspension": "Hydraulic monoshock",
    "rear_wheel_travel": null,
    "front_tire": "130/60-R13 ",
    "rear_tire": "130/60-R13 ",
    "front_brakes": "Single disc",
    "rear_brakes": "Single disc",
    "seat_height": "790 mm (31.1 inches) If adjustable, lowest setting.",
    "ground_clearance": null,
    "wheelbase": null,
    "fuel_capacity": null,
    "starter": "Electric",
    "power": "4.0 HP (2.9  kW))",
    "torque": "54.0 Nm (5.5 kgf-m or 39.8 ft.lbs)",
    "top_speed": "45.0 km/h (28.0 mph)",
    "fuel_consumption": null,
    "emission": null,
    "total_weight": "118.0 kg (260.1 pounds)",
    "total_height": null,
    "total_length": "1800 mm (70.9 inches)",
    "total_width": "685 mm (27.0 inches)",
    "ignition": null,
    "dry_weight": null
  },
  {
    "make": "Govecs",
    "model": "Pro Cargo",
    "year": "2020",
    "type": "Scooter",
    "displacement": null,
    "engine": "Electric",
    "compression": null,
    "bore_stroke": null,
    "valves_per_cylinder": null,
    "fuel_system": null,
    "fuel_control": null,
    "lubrication": null,
    "cooling": "Air",
    "gearbox": "1-speed",
    "transmission": "Belt   (final drive)",
    "clutch": null,
    "frame": "Steel tube",
    "front_suspension": "Hydraulic telescope",
    "front_wheel_travel": null,
    "rear_suspension": "Hydraulic monoshock",
    "rear_wheel_travel": null,
    "front_tire": "130/60-R13 ",
    "rear_tire": "130/60-R13 ",
    "front_brakes": "Single disc",
    "rear_brakes": "Single disc",
    "seat_height": "810 mm (31.9 inches) If adjustable, lowest setting.",
    "ground_clearance": null,
    "wheelbase": null,
    "fuel_capacity": null,
    "starter": "Electric",
    "power": "5.4 HP (3.9  kW))",
    "torque": "54.0 Nm (5.5 kgf-m or 39.8 ft.lbs)",
    "top_speed": "45.0 km/h (28.0 mph)",
    "fuel_consumption": null,
    "emission": null,
    "total_weight": "129.0 kg (284.4 pounds)",
    "total_height": "1250 mm (49.2 inches)",
    "total_length": "2050 mm (80.7 inches)",
    "total_width": "750 mm (29.5 inches)",
    "ignition": null,
    "dry_weight": null
  },
  {
    "make": "Govecs",
    "model": "GO! S2.6",
    "year": "2016",
    "type": "Scooter",
    "displacement": null,
    "engine": "Electric",
    "compression": null,
    "bore_stroke": null,
    "valves_per_cylinder": null,
    "fuel_system": null,
    "fuel_control": null,
    "lubrication": null,
    "cooling": "Air",
    "gearbox": "1-speed",
    "transmission": "Belt   (final drive)",
    "clutch": null,
    "frame": "Steel tube",
    "front_suspension": "Hydraulic telescope",
    "front_wheel_travel": null,
    "rear_suspension": "Hydraulic monoshock",
    "rear_wheel_travel": null,
    "front_tire": "130/60-R13 ",
    "rear_tire": "130/60-R13 ",
    "front_brakes": "Single disc. Regenerative braking",
    "rear_brakes": "Expanding brake (drum brake). Regenerative braking",
    "seat_height": "790 mm (31.1 inches) If adjustable, lowest setting.",
    "ground_clearance": null,
    "wheelbase": "1300 mm (51.2 inches)",
    "fuel_capacity": null,
    "starter": "Electric",
    "power": "4.0 HP (2.9  kW))",
    "torque": "54.0 Nm (5.5 kgf-m or 39.8 ft.lbs)",
    "top_speed": "45.0 km/h (28.0 mph)",
    "fuel_consumption": null,
    "emission": null,
    "total_weight": "130.0 kg (286.6 pounds)",
    "total_height": null,
    "total_length": null,
    "total_width": null,
    "ignition": null,
    "dry_weight": null
  },
  {
    "make": "Govecs",
    "model": "GO! T2.6",
    "year": "2016",
    "type": "Scooter",
    "displacement": null,
    "engine": "Electric",
    "compression": null,
    "bore_stroke": null,
    "valves_per_cylinder": null,
    "fuel_system": null,
    "fuel_control": null,
    "lubrication": null,
    "cooling": "Air",
    "gearbox": "1-speed",
    "transmission": "Belt   (final drive)",
    "clutch": null,
    "frame": "Steel tube",
    "front_suspension": "Hydraulic telescope",
    "front_wheel_travel": null,
    "rear_suspension": "Monoshock",
    "rear_wheel_travel": null,
    "front_tire": "130/60-R13 ",
    "rear_tire": "130/60-R13 ",
    "front_brakes": "Single disc. Regenerative braking",
    "rear_brakes": "Expanding brake (drum brake). Regenerative braking",
    "seat_height": "790 mm (31.1 inches) If adjustable, lowest setting.",
    "ground_clearance": null,
    "wheelbase": "1300 mm (51.2 inches)",
    "fuel_capacity": null,
    "starter": "Electric",
    "power": "4.0 HP (2.9  kW))",
    "torque": "54.0 Nm (5.5 kgf-m or 39.8 ft.lbs)",
    "top_speed": "45.0 km/h (28.0 mph)",
    "fuel_consumption": null,
    "emission": null,
    "total_weight": "130.0 kg (286.6 pounds)",
    "total_height": null,
    "total_length": null,
    "total_width": null,
    "ignition": null,
    "dry_weight": null
  },
  {
    "make": "Govecs",
    "model": "GiGi",
    "year": "2016",
    "type": "Scooter",
    "displacement": null,
    "engine": "Electric",
    "compression": null,
    "bore_stroke": null,
    "valves_per_cylinder": null,
    "fuel_system": null,
    "fuel_control": null,
    "lubrication": null,
    "cooling": "Air",
    "gearbox": "1-speed",
    "transmission": null,
    "clutch": null,
    "frame": "Foldable fram",
    "front_suspension": null,
    "front_wheel_travel": null,
    "rear_suspension": null,
    "rear_wheel_travel": null,
    "front_tire": null,
    "rear_tire": null,
    "front_brakes": "Expanding brake (drum brake)",
    "rear_brakes": "Expanding brake (drum brake)",
    "seat_height": null,
    "ground_clearance": null,
    "wheelbase": "920 mm (36.2 inches)",
    "fuel_capacity": null,
    "starter": "Electric",
    "power": null,
    "torque": null,
    "top_speed": "25.0 km/h (15.5 mph)",
    "fuel_consumption": null,
    "emission": null,
    "total_weight": null,
    "total_height": null,
    "total_length": null,
    "total_width": null,
    "ignition": null,
    "dry_weight": "30.0 kg (66.1 pounds)"
  },
  {
    "make": "Govecs",
    "model": "Sway",
    "year": "2016",
    "type": "Scooter",
    "displacement": null,
    "engine": "Electric",
    "compression": null,
    "bore_stroke": null,
    "valves_per_cylinder": null,
    "fuel_system": null,
    "fuel_control": null,
    "lubrication": null,
    "cooling": "Air",
    "gearbox": "1-speed",
    "transmission": null,
    "clutch": null,
    "frame": null,
    "front_suspension": "Telescopic fork",
    "front_wheel_travel": null,
    "rear_suspension": "Monoshock",
    "rear_wheel_travel": null,
    "front_tire": null,
    "rear_tire": null,
    "front_brakes": "Single disc",
    "rear_brakes": "Single disc",
    "seat_height": null,
    "ground_clearance": null,
    "wheelbase": null,
    "fuel_capacity": null,
    "starter": "Electric",
    "power": "6.7 HP (4.9  kW))",
    "torque": null,
    "top_speed": "88.5 km/h (55.0 mph)",
    "fuel_consumption": null,
    "emission": null,
    "total_weight": null,
    "total_height": "914 mm (36.0 inches)",
    "total_length": "1651 mm (65.0 inches)",
    "total_width": "1143 mm (45.0 inches)",
    "ignition": null,
    "dry_weight": "113.4 kg (250.0 pounds)"
  },
  {
    "make": "Govecs",
    "model": "Tripl",
    "year": "2016",
    "type": "Scooter",
    "displacement": null,
    "engine": "Electric",
    "compression": null,
    "bore_stroke": null,
    "valves_per_cylinder": null,
    "fuel_system": null,
    "fuel_control": null,
    "lubrication": null,
    "cooling": "Air",
    "gearbox": "1-speed",
    "transmission": null,
    "clutch": null,
    "frame": null,
    "front_suspension": "Telescopic fork",
    "front_wheel_travel": null,
    "rear_suspension": "Monoshock",
    "rear_wheel_travel": null,
    "front_tire": null,
    "rear_tire": null,
    "front_brakes": "Single disc",
    "rear_brakes": "Single disc",
    "seat_height": null,
    "ground_clearance": null,
    "wheelbase": "1500 mm (59.1 inches)",
    "fuel_capacity": null,
    "starter": "Electric",
    "power": null,
    "torque": "190.0 Nm (19.4 kgf-m or 140.1 ft.lbs)",
    "top_speed": "45.0 km/h (28.0 mph)",
    "fuel_consumption": null,
    "emission": null,
    "total_weight": null,
    "total_height": null,
    "total_length": null,
    "total_width": null,
    "ignition": null,
    "dry_weight": "301.0 kg (663.6 pounds)"
  },
  {
    "make": "Govecs",
    "model": "GO S1.3",
    "year": "2015",
    "type": "Scooter",
    "displacement": null,
    "engine": "Electric",
    "compression": null,
    "bore_stroke": null,
    "valves_per_cylinder": null,
    "fuel_system": null,
    "fuel_control": null,
    "lubrication": null,
    "cooling": "Air",
    "gearbox": "1-speed",
    "transmission": "Belt   (final drive)",
    "clutch": null,
    "frame": "Steel tube frame",
    "front_suspension": "Hydraulic telescope",
    "front_wheel_travel": null,
    "rear_suspension": "Hydraulic monoshock",
    "rear_wheel_travel": null,
    "front_tire": "130/60-R13 ",
    "rear_tire": "130/60-R13 ",
    "front_brakes": "Single disc",
    "rear_brakes": "Expanding brake (drum brake). Regenerative braking",
    "seat_height": "790 mm (31.1 inches) If adjustable, lowest setting.",
    "ground_clearance": null,
    "wheelbase": "1300 mm (51.2 inches)",
    "fuel_capacity": null,
    "starter": "Electric",
    "power": null,
    "torque": null,
    "top_speed": "45.0 km/h (28.0 mph)",
    "fuel_consumption": null,
    "emission": null,
    "total_weight": null,
    "total_height": null,
    "total_length": null,
    "total_width": null,
    "ignition": null,
    "dry_weight": "100.0 kg (220.5 pounds)"
  },
  {
    "make": "Govecs",
    "model": "GO T 1.4",
    "year": "2014",
    "type": "Scooter",
    "displacement": null,
    "engine": "Electric",
    "compression": null,
    "bore_stroke": null,
    "valves_per_cylinder": null,
    "fuel_system": null,
    "fuel_control": null,
    "lubrication": null,
    "cooling": "Air",
    "gearbox": "1-speed",
    "transmission": "Belt   (final drive)",
    "clutch": null,
    "frame": null,
    "front_suspension": "Telescopic fork",
    "front_wheel_travel": null,
    "rear_suspension": "Monoshock",
    "rear_wheel_travel": null,
    "front_tire": "130/60-R13 ",
    "rear_tire": "130/60-13 ",
    "front_brakes": "Single disc. Hydraulic",
    "rear_brakes": "Single disc. Hydraulic",
    "seat_height": "790 mm (31.1 inches) If adjustable, lowest setting.",
    "ground_clearance": null,
    "wheelbase": "1300 mm (51.2 inches)",
    "fuel_capacity": null,
    "starter": "Electric",
    "power": null,
    "torque": "54.0 Nm (5.5 kgf-m or 39.8 ft.lbs)",
    "top_speed": "45.0 km/h (28.0 mph)",
    "fuel_consumption": null,
    "emission": null,
    "total_weight": null,
    "total_height": null,
    "total_length": null,
    "total_width": null,
    "ignition": null,
    "dry_weight": "100.0 kg (220.5 pounds)"
  },
  {
    "make": "Govecs",
    "model": "GO T 2.4",
    "year": "2014",
    "type": "Scooter",
    "displacement": null,
    "engine": "Electric",
    "compression": null,
    "bore_stroke": null,
    "valves_per_cylinder": null,
    "fuel_system": null,
    "fuel_control": null,
    "lubrication": null,
    "cooling": "Air",
    "gearbox": "1-speed",
    "transmission": "Belt   (final drive)",
    "clutch": null,
    "frame": "Steel",
    "front_suspension": "Telescopic fork",
    "front_wheel_travel": null,
    "rear_suspension": "Monoshock",
    "rear_wheel_travel": null,
    "front_tire": "130/60-R13 ",
    "rear_tire": "130/60-R13 ",
    "front_brakes": "Single disc. Hydraulic",
    "rear_brakes": "Single disc. Hydraulic",
    "seat_height": "790 mm (31.1 inches) If adjustable, lowest setting.",
    "ground_clearance": null,
    "wheelbase": "1300 mm (51.2 inches)",
    "fuel_capacity": null,
    "starter": "Electric",
    "power": null,
    "torque": "54.0 Nm (5.5 kgf-m or 39.8 ft.lbs)",
    "top_speed": "45.0 km/h (28.0 mph)",
    "fuel_consumption": null,
    "emission": null,
    "total_weight": null,
    "total_height": null,
    "total_length": null,
    "total_width": null,
    "ignition": null,
    "dry_weight": "115.0 kg (253.5 pounds)"
  },
  {
    "make": "Govecs",
    "model": "GO T 3.4",
    "year": "2014",
    "type": "Scooter",
    "displacement": null,
    "engine": "Electric",
    "compression": null,
    "bore_stroke": null,
    "valves_per_cylinder": null,
    "fuel_system": null,
    "fuel_control": null,
    "lubrication": null,
    "cooling": "Air",
    "gearbox": "1-speed",
    "transmission": "Belt   (final drive)",
    "clutch": null,
    "frame": "Steel",
    "front_suspension": "Telescopic fork",
    "front_wheel_travel": null,
    "rear_suspension": "Monoshock",
    "rear_wheel_travel": null,
    "front_tire": "130/60-R13 ",
    "rear_tire": "130/60-R13 ",
    "front_brakes": "Single disc. Hydraulic",
    "rear_brakes": "Single disc. Hydraulic",
    "seat_height": "790 mm (31.1 inches) If adjustable, lowest setting.",
    "ground_clearance": null,
    "wheelbase": "1300 mm (51.2 inches)",
    "fuel_capacity": null,
    "starter": "Electric",
    "power": null,
    "torque": "114.0 Nm (11.6 kgf-m or 84.1 ft.lbs)",
    "top_speed": "80.0 km/h (49.7 mph)",
    "fuel_consumption": null,
    "emission": null,
    "total_weight": null,
    "total_height": null,
    "total_length": null,
    "total_width": null,
    "ignition": null,
    "dry_weight": "115.0 kg (253.5 pounds)"
  },
  {
    "make": "Govecs",
    "model": "GO S 3.4",
    "year": "2012",
    "type": "Scooter",
    "displacement": null,
    "engine": "Electric",
    "compression": null,
    "bore_stroke": null,
    "valves_per_cylinder": null,
    "fuel_system": null,
    "fuel_control": null,
    "lubrication": null,
    "cooling": "Air",
    "gearbox": "1-speed",
    "transmission": "Belt   (final drive)",
    "clutch": null,
    "frame": "Steel tube",
    "front_suspension": "Hydraulic telescope",
    "front_wheel_travel": null,
    "rear_suspension": "Hydraulic shocks",
    "rear_wheel_travel": null,
    "front_tire": "130/60-R13 ",
    "rear_tire": "130/60-R13 ",
    "front_brakes": "Single disc. Regenerative braking",
    "rear_brakes": "Single disc. Regenerative braking",
    "seat_height": "790 mm (31.1 inches) If adjustable, lowest setting.",
    "ground_clearance": null,
    "wheelbase": "1330 mm (52.4 inches)",
    "fuel_capacity": null,
    "starter": "Electric",
    "power": "4.5 HP (3.3  kW))",
    "torque": "114.0 Nm (11.6 kgf-m or 84.1 ft.lbs)",
    "top_speed": "85.0 km/h (52.8 mph)",
    "fuel_consumption": null,
    "emission": null,
    "total_weight": null,
    "total_height": null,
    "total_length": null,
    "total_width": null,
    "ignition": null,
    "dry_weight": "120.0 kg (264.6 pounds)"
  },
  {
    "make": "Govecs",
    "model": "GO C 1.4",
    "year": "2011",
    "type": "Scooter",
    "displacement": null,
    "engine": "Electric",
    "compression": null,
    "bore_stroke": null,
    "valves_per_cylinder": null,
    "fuel_system": null,
    "fuel_control": null,
    "lubrication": null,
    "cooling": "Air",
    "gearbox": "1-speed",
    "transmission": "Belt   (final drive)",
    "clutch": null,
    "frame": "Lightweight design",
    "front_suspension": "Hydraulic telescope",
    "front_wheel_travel": null,
    "rear_suspension": "Hydraulic",
    "rear_wheel_travel": null,
    "front_tire": "110/70-12 ",
    "rear_tire": "110/70-12 ",
    "front_brakes": "Single disc. Floating disk",
    "rear_brakes": "Single disc. Floating disk",
    "seat_height": "790 mm (31.1 inches) If adjustable, lowest setting.",
    "ground_clearance": null,
    "wheelbase": "1275 mm (50.2 inches)",
    "fuel_capacity": null,
    "starter": "Electric",
    "power": "4.0 HP (2.9  kW))",
    "torque": "7.0 Nm (0.7 kgf-m or 5.2 ft.lbs)",
    "top_speed": "45.0 km/h (28.0 mph)",
    "fuel_consumption": null,
    "emission": null,
    "total_weight": null,
    "total_height": null,
    "total_length": null,
    "total_width": null,
    "ignition": null,
    "dry_weight": "80.0 kg (176.4 pounds)"
  },
  {
    "make": "Govecs",
    "model": "GO S 1.2",
    "year": "2011",
    "type": "Scooter",
    "displacement": null,
    "engine": "Electric",
    "compression": null,
    "bore_stroke": null,
    "valves_per_cylinder": null,
    "fuel_system": null,
    "fuel_control": null,
    "lubrication": null,
    "cooling": "Air",
    "gearbox": "1-speed",
    "transmission": "Belt   (final drive)",
    "clutch": null,
    "frame": "Steel tube frame",
    "front_suspension": "Hydraulic telescope",
    "front_wheel_travel": null,
    "rear_suspension": "Hydraulic",
    "rear_wheel_travel": null,
    "front_tire": "130/60-R13 ",
    "rear_tire": "130/60-R13 ",
    "front_brakes": "Single disc",
    "rear_brakes": "Expanding brake (drum brake). Regenerative braking",
    "seat_height": "790 mm (31.1 inches) If adjustable, lowest setting.",
    "ground_clearance": null,
    "wheelbase": "1330 mm (52.4 inches)",
    "fuel_capacity": null,
    "starter": "Electric",
    "power": "4.0 HP (2.9  kW))",
    "torque": "9.0 Nm (0.9 kgf-m or 6.6 ft.lbs)",
    "top_speed": "45.0 km/h (28.0 mph)",
    "fuel_consumption": null,
    "emission": null,
    "total_weight": null,
    "total_height": null,
    "total_length": null,
    "total_width": null,
    "ignition": null,
    "dry_weight": "135.0 kg (297.6 pounds)"
  },
  {
    "make": "Govecs",
    "model": "GO S 2.4",
    "year": "2011",
    "type": "Scooter",
    "displacement": null,
    "engine": "Electric",
    "compression": null,
    "bore_stroke": null,
    "valves_per_cylinder": null,
    "fuel_system": null,
    "fuel_control": null,
    "lubrication": null,
    "cooling": "Air",
    "gearbox": "1-speed",
    "transmission": "Belt   (final drive)",
    "clutch": null,
    "frame": "Steel tube",
    "front_suspension": "Hydraulic telescope",
    "front_wheel_travel": null,
    "rear_suspension": "Hydraulic",
    "rear_wheel_travel": null,
    "front_tire": "130/60-R13 ",
    "rear_tire": "130/60-R13 ",
    "front_brakes": "Single disc. Regenerative braking",
    "rear_brakes": "Expanding brake (drum brake). Regenerative braking",
    "seat_height": "790 mm (31.1 inches) If adjustable, lowest setting.",
    "ground_clearance": null,
    "wheelbase": "1330 mm (52.4 inches)",
    "fuel_capacity": null,
    "starter": "Electric",
    "power": "4.0 HP (2.9  kW))",
    "torque": "9.0 Nm (0.9 kgf-m or 6.6 ft.lbs)",
    "top_speed": "45.0 km/h (28.0 mph)",
    "fuel_consumption": null,
    "emission": null,
    "total_weight": null,
    "total_height": null,
    "total_length": null,
    "total_width": null,
    "ignition": null,
    "dry_weight": "115.0 kg (253.5 pounds)"
  },
  {
    "make": "Govecs",
    "model": "SC 1.4",
    "year": "2010",
    "type": "Scooter",
    "displacement": null,
    "engine": "Electric",
    "compression": null,
    "bore_stroke": null,
    "valves_per_cylinder": null,
    "fuel_system": null,
    "fuel_control": null,
    "lubrication": null,
    "cooling": "Air",
    "gearbox": "1-speed",
    "transmission": "Belt   (final drive)",
    "clutch": null,
    "frame": "Lightweight design",
    "front_suspension": "Hydraulic telescope",
    "front_wheel_travel": null,
    "rear_suspension": "Hydraulic",
    "rear_wheel_travel": null,
    "front_tire": null,
    "rear_tire": null,
    "front_brakes": "Single disc",
    "rear_brakes": "Expanding brake (drum brake)",
    "seat_height": "790 mm (31.1 inches) If adjustable, lowest setting.",
    "ground_clearance": null,
    "wheelbase": "1275 mm (50.2 inches)",
    "fuel_capacity": null,
    "starter": "Electric",
    "power": "4.0 HP (2.9  kW))",
    "torque": "7.0 Nm (0.7 kgf-m or 5.2 ft.lbs)",
    "top_speed": "45.0 km/h (28.0 mph)",
    "fuel_consumption": null,
    "emission": null,
    "total_weight": null,
    "total_height": null,
    "total_length": null,
    "total_width": null,
    "ignition": null,
    "dry_weight": "80.0 kg (176.4 pounds)"
  },
  {
    "make": "Govecs",
    "model": "SR 1.2",
    "year": "2010",
    "type": "Scooter",
    "displacement": null,
    "engine": "Electric",
    "compression": null,
    "bore_stroke": null,
    "valves_per_cylinder": null,
    "fuel_system": null,
    "fuel_control": null,
    "lubrication": null,
    "cooling": null,
    "gearbox": "Automatic",
    "transmission": "Belt   (final drive)",
    "clutch": null,
    "frame": "Steel tube",
    "front_suspension": "Hydraulic telescope",
    "front_wheel_travel": null,
    "rear_suspension": "Hydraulic mono suspension",
    "rear_wheel_travel": null,
    "front_tire": "130/60-13 ",
    "rear_tire": "130/60-13 ",
    "front_brakes": "Single disc",
    "rear_brakes": "Expanding brake (drum brake)",
    "seat_height": "790 mm (31.1 inches) If adjustable, lowest setting.",
    "ground_clearance": null,
    "wheelbase": "1330 mm (52.4 inches)",
    "fuel_capacity": null,
    "starter": "Electric",
    "power": "5.4 HP (3.9  kW))",
    "torque": "8.8 Nm (0.9 kgf-m or 6.5 ft.lbs)",
    "top_speed": "45.0 km/h (28.0 mph)",
    "fuel_consumption": null,
    "emission": null,
    "total_weight": null,
    "total_height": null,
    "total_length": null,
    "total_width": null,
    "ignition": null,
    "dry_weight": "136.0 kg (299.8 pounds)"
  }
]
